hypermodern_python_test/__init__.py
hypermodern_python_test/console.py
hypermodern_python_test/wikipedia.py
hypermodern_python_test-0.1.5.dist-info/entry_points.txt
hypermodern_python_test-0.1.5.dist-info/LICENSE
hypermodern_python_test-0.1.5.dist-info/WHEEL
hypermodern_python_test-0.1.5.dist-info/METADATA
hypermodern_python_test-0.1.5.dist-info/RECORD
