Metadata-Version: 2.1
Name: hypermodern-python-test
Version: 0.1.5
Summary: The hypermodern Python project
Home-page: https://github.com/bluemania/hypermodern-python
License: MIT
Keywords: hypermodern
Author: bluemania
Author-email: damnthatswack@hotmail.com
Requires-Python: >=3.7,<4.0
Classifier: License :: OSI Approved :: MIT License
Classifier: Programming Language :: Python :: 3
Classifier: Programming Language :: Python :: 3.7
Classifier: Programming Language :: Python :: 3.8
Requires-Dist: click (>=7.1.2,<8.0.0)
Requires-Dist: desert (>=2020.1.6,<2021.0.0)
Requires-Dist: importlib_metadata (>=1.7.0,<2.0.0)
Requires-Dist: marshmallow (>=3.7.1,<4.0.0)
Requires-Dist: requests (>=2.24.0,<3.0.0)
Project-URL: Repository, https://github.com/bluemania/hypermodern-python
